{"45001": {"statePostal": "UT", "reportingunitName": "Beaver", "reportingunitID": "45001", "reportingunitLevel": 2, "pollClosingTime": "2024-11-06T03:00:00.000000Z", "level": "subunit", "fipsCode": "49001", "electTotal": 6, "lastUpdated": "2024-12-05T19:39:17.391000Z", "precinctsReporting": 9, "eevp": 100.0, "precinctsTotal": 9, "precinctsReportingPct": 100.0, "candidates": [{"candidateID": "8639", "voteCount": 2781, "votePct": 86.58}, {"candidateID": "64984", "voteCount": 394, "votePct": 12.27}, {"candidateID": "167871", "voteCount": 14, "votePct": 0.44}, {"candidateID": "69459", "voteCount": 10, "votePct": 0.31}, {"candidateID": "895", "voteCount": 8, "votePct": 0.25}, {"candidateID": "73180", "voteCount": 4, "votePct": 0.12}, {"candidateID": "167488", "voteCount": 1, "votePct": 0.03}, {"candidateID": "71845", "voteCount": 0, "votePct": 0.0}], "parameters": {"vote": {"expected": {"actual": 3212, "eevpCap": 100.0}, "total": 3212, "registered": 4048}, "precinctsReportingActual": 9, "precinctsReportingProportional": 9}}, "45002": {"statePostal": "UT", "reportingunitName": "Box Elder", "reportingunitID": "45002", "reportingunitLevel": 2, "pollClosingTime": "2024-11-06T03:00:00.000000Z", "level": "subunit", "fipsCode": "49003", "electTotal": 6, "lastUpdated": "2024-12-05T19:39:17.391000Z", "precinctsReporting": 53, "eevp": 100.0, "precinctsTotal": 53, "precinctsReportingPct": 100.0, "candidates": [{"candidateID": "8639", "voteCount": 22853, "votePct": 79.05}, {"candidateID": "64984", "voteCount": 5274, "votePct": 18.24}, {"candidateID": "69459", "voteCount": 342, "votePct": 1.18}, {"candidateID": "167871", "voteCount": 196, "votePct": 0.68}, {"candidateID": "895", "voteCount": 119, "votePct": 0.41}, {"candidateID": "167488", "voteCount": 49, "votePct": 0.17}, {"candidateID": "73180", "voteCount": 44, "votePct": 0.15}, {"candidateID": "71845", "voteCount": 32, "votePct": 0.11}], "parameters": {"vote": {"expected": {"actual": 28909, "eevpCap": 100.0}, "total": 28909, "registered": 36865}, "precinctsReportingActual": 53, "precinctsReportingProportional": 53}}, "45003": {"statePostal": "UT", "reportingunitName": "Cache", "reportingunitID": "45003", "reportingunitLevel": 2, "pollClosingTime": "2024-11-06T03:00:00.000000Z", "level": "subunit", "fipsCode": "49005", "electTotal": 6, "lastUpdated": "2024-12-05T19:39:17.391000Z", "precinctsReporting": 167, "eevp": 100.0, "precinctsTotal": 167, "precinctsReportingPct": 100.0, "candidates": [{"candidateID": "8639", "voteCount": 39457, "votePct": 65.51}, {"candidateID": "64984", "voteCount": 18718, "votePct": 31.08}, {"candidateID": "69459", "voteCount": 885, "votePct": 1.47}, {"candidateID": "167871", "voteCount": 506, "votePct": 0.84}, {"candidateID": "895", "voteCount": 343, "votePct": 0.57}, {"candidateID": "73180", "voteCount": 119, "votePct": 0.2}, {"candidateID": "167488", "voteCount": 107, "votePct": 0.18}, {"candidateID": "71845", "voteCount": 94, "votePct": 0.16}], "parameters": {"vote": {"expected": {"actual": 60229, "eevpCap": 100.0}, "total": 60229, "registered": 79984}, "precinctsReportingActual": 167, "precinctsReportingProportional": 167}}, "45004": {"statePostal": "UT", "reportingunitName": "Carbon", "reportingunitID": "45004", "reportingunitLevel": 2, "pollClosingTime": "2024-11-06T03:00:00.000000Z", "level": "subunit", "fipsCode": "49007", "electTotal": 6, "lastUpdated": "2024-12-05T19:39:17.391000Z", "precinctsReporting": 21, "eevp": 100.0, "precinctsTotal": 21, "precinctsReportingPct": 100.0, "candidates": [{"candidateID": "8639", "voteCount": 6719, "votePct": 71.14}, {"candidateID": "64984", "voteCount": 2525, "votePct": 26.73}, {"candidateID": "69459", "voteCount": 90, "votePct": 0.95}, {"candidateID": "895", "voteCount": 38, "votePct": 0.4}, {"candidateID": "167871", "voteCount": 32, "votePct": 0.34}, {"candidateID": "167488", "voteCount": 19, "votePct": 0.2}, {"candidateID": "73180", "voteCount": 14, "votePct": 0.15}, {"candidateID": "71845", "voteCount": 8, "votePct": 0.08}], "parameters": {"vote": {"expected": {"actual": 9445, "eevpCap": 100.0}, "total": 9445, "registered": 12661}, "precinctsReportingActual": 21, "precinctsReportingProportional": 21}}, "45005": {"statePostal": "UT", "reportingunitName": "Daggett", "reportingunitID": "45005", "reportingunitLevel": 2, "pollClosingTime": "2024-11-06T03:00:00.000000Z", "level": "subunit", "fipsCode": "49009", "electTotal": 6, "lastUpdated": "2024-12-05T19:39:17.391000Z", "precinctsReporting": 4, "eevp": 100.0, "precinctsTotal": 4, "precinctsReportingPct": 100.0, "candidates": [{"candidateID": "8639", "voteCount": 443, "votePct": 80.55}, {"candidateID": "64984", "voteCount": 101, "votePct": 18.36}, {"candidateID": "69459", "voteCount": 2, "votePct": 0.36}, {"candidateID": "895", "voteCount": 2, "votePct": 0.36}, {"candidateID": "167871", "voteCount": 1, "votePct": 0.18}, {"candidateID": "71845", "voteCount": 1, "votePct": 0.18}, {"candidateID": "167488", "voteCount": 0, "votePct": 0.0}, {"candidateID": "73180", "voteCount": 0, "votePct": 0.0}], "parameters": {"vote": {"expected": {"actual": 550, "eevpCap": 100.0}, "total": 550, "registered": 720}, "precinctsReportingActual": 4, "precinctsReportingProportional": 4}}, "45006": {"statePostal": "UT", "reportingunitName": "Davis", "reportingunitID": "45006", "reportingunitLevel": 2, "pollClosingTime": "2024-11-06T03:00:00.000000Z", "level": "subunit", "fipsCode": "49011", "electTotal": 6, "lastUpdated": "2024-12-05T19:39:17.391000Z", "precinctsReporting": 438, "eevp": 100.0, "precinctsTotal": 438, "precinctsReportingPct": 100.0, "candidates": [{"candidateID": "8639", "voteCount": 101293, "votePct": 60.84}, {"candidateID": "64984", "voteCount": 59895, "votePct": 35.97}, {"candidateID": "69459", "voteCount": 2137, "votePct": 1.28}, {"candidateID": "167871", "voteCount": 1208, "votePct": 0.73}, {"candidateID": "895", "voteCount": 890, "votePct": 0.53}, {"candidateID": "73180", "voteCount": 413, "votePct": 0.25}, {"candidateID": "167488", "voteCount": 365, "votePct": 0.22}, {"candidateID": "71845", "voteCount": 291, "votePct": 0.17}], "parameters": {"vote": {"expected": {"actual": 166492, "eevpCap": 100.0}, "total": 166492, "registered": 224329}, "precinctsReportingActual": 438, "precinctsReportingProportional": 438}}, "45007": {"statePostal": "UT", "reportingunitName": "Duchesne", "reportingunitID": "45007", "reportingunitLevel": 2, "pollClosingTime": "2024-11-06T03:00:00.000000Z", "level": "subunit", "fipsCode": "49013", "electTotal": 6, "lastUpdated": "2024-12-05T19:39:17.391000Z", "precinctsReporting": 81, "eevp": 100.0, "precinctsTotal": 81, "precinctsReportingPct": 100.0, "candidates": [{"candidateID": "8639", "voteCount": 7815, "votePct": 87.15}, {"candidateID": "64984", "voteCount": 1009, "votePct": 11.25}, {"candidateID": "167871", "voteCount": 53, "votePct": 0.59}, {"candidateID": "69459", "voteCount": 45, "votePct": 0.5}, {"candidateID": "895", "voteCount": 16, "votePct": 0.18}, {"candidateID": "73180", "voteCount": 14, "votePct": 0.16}, {"candidateID": "167488", "voteCount": 8, "votePct": 0.09}, {"candidateID": "71845", "voteCount": 7, "votePct": 0.08}], "parameters": {"vote": {"expected": {"actual": 8967, "eevpCap": 100.0}, "total": 8967, "registered": 11734}, "precinctsReportingActual": 81, "precinctsReportingProportional": 81}}, "45008": {"statePostal": "UT", "reportingunitName": "Emery", "reportingunitID": "45008", "reportingunitLevel": 2, "pollClosingTime": "2024-11-06T03:00:00.000000Z", "level": "subunit", "fipsCode": "49015", "electTotal": 6, "lastUpdated": "2024-12-05T19:39:17.391000Z", "precinctsReporting": 13, "eevp": 100.0, "precinctsTotal": 13, "precinctsReportingPct": 100.0, "candidates": [{"candidateID": "8639", "voteCount": 4341, "votePct": 86.63}, {"candidateID": "64984", "voteCount": 603, "votePct": 12.03}, {"candidateID": "69459", "voteCount": 32, "votePct": 0.64}, {"candidateID": "167871", "voteCount": 17, "votePct": 0.34}, {"candidateID": "895", "voteCount": 8, "votePct": 0.16}, {"candidateID": "167488", "voteCount": 5, "votePct": 0.1}, {"candidateID": "71845", "voteCount": 3, "votePct": 0.06}, {"candidateID": "73180", "voteCount": 2, "votePct": 0.04}], "parameters": {"vote": {"expected": {"actual": 5011, "eevpCap": 100.0}, "total": 5011, "registered": 6413}, "precinctsReportingActual": 13, "precinctsReportingProportional": 13}}, "45009": {"statePostal": "UT", "reportingunitName": "Garfield", "reportingunitID": "45009", "reportingunitLevel": 2, "pollClosingTime": "2024-11-06T03:00:00.000000Z", "level": "subunit", "fipsCode": "49017", "electTotal": 6, "lastUpdated": "2024-12-05T19:39:17.391000Z", "precinctsReporting": 12, "eevp": 100.0, "precinctsTotal": 12, "precinctsReportingPct": 100.0, "candidates": [{"candidateID": "8639", "voteCount": 2211, "votePct": 78.66}, {"candidateID": "64984", "voteCount": 541, "votePct": 19.25}, {"candidateID": "167871", "voteCount": 18, "votePct": 0.64}, {"candidateID": "895", "voteCount": 17, "votePct": 0.6}, {"candidateID": "69459", "voteCount": 15, "votePct": 0.53}, {"candidateID": "73180", "voteCount": 5, "votePct": 0.18}, {"candidateID": "167488", "voteCount": 3, "votePct": 0.11}, {"candidateID": "71845", "voteCount": 1, "votePct": 0.04}], "parameters": {"vote": {"expected": {"actual": 2811, "eevpCap": 100.0}, "total": 2811, "registered": 3398}, "precinctsReportingActual": 12, "precinctsReportingProportional": 12}}, "45010": {"statePostal": "UT", "reportingunitName": "Grand", "reportingunitID": "45010", "reportingunitLevel": 2, "pollClosingTime": "2024-11-06T03:00:00.000000Z", "level": "subunit", "fipsCode": "49019", "electTotal": 6, "lastUpdated": "2024-12-05T19:39:17.391000Z", "precinctsReporting": 24, "eevp": 100.0, "precinctsTotal": 24, "precinctsReportingPct": 100.0, "candidates": [{"candidateID": "64984", "voteCount": 2828, "votePct": 53.36}, {"candidateID": "8639", "voteCount": 2327, "votePct": 43.91}, {"candidateID": "895", "voteCount": 49, "votePct": 0.92}, {"candidateID": "69459", "voteCount": 25, "votePct": 0.47}, {"candidateID": "167488", "voteCount": 20, "votePct": 0.38}, {"candidateID": "167871", "voteCount": 20, "votePct": 0.38}, {"candidateID": "71845", "voteCount": 16, "votePct": 0.3}, {"candidateID": "73180", "voteCount": 15, "votePct": 0.28}], "parameters": {"vote": {"expected": {"actual": 5300, "eevpCap": 100.0}, "total": 5300, "registered": 6737}, "precinctsReportingActual": 24, "precinctsReportingProportional": 24}}, "45011": {"statePostal": "UT", "reportingunitName": "Iron", "reportingunitID": "45011", "reportingunitLevel": 2, "pollClosingTime": "2024-11-06T03:00:00.000000Z", "level": "subunit", "fipsCode": "49021", "electTotal": 6, "lastUpdated": "2024-12-05T19:39:17.391000Z", "precinctsReporting": 50, "eevp": 100.0, "precinctsTotal": 50, "precinctsReportingPct": 100.0, "candidates": [{"candidateID": "8639", "voteCount": 21571, "votePct": 77.38}, {"candidateID": "64984", "voteCount": 5683, "votePct": 20.39}, {"candidateID": "69459", "voteCount": 275, "votePct": 0.99}, {"candidateID": "167871", "voteCount": 154, "votePct": 0.55}, {"candidateID": "895", "voteCount": 87, "votePct": 0.31}, {"candidateID": "167488", "voteCount": 40, "votePct": 0.14}, {"candidateID": "73180", "voteCount": 35, "votePct": 0.13}, {"candidateID": "71845", "voteCount": 31, "votePct": 0.11}], "parameters": {"vote": {"expected": {"actual": 27876, "eevpCap": 100.0}, "total": 27876, "registered": 36906}, "precinctsReportingActual": 50, "precinctsReportingProportional": 50}}, "45012": {"statePostal": "UT", "reportingunitName": "Juab", "reportingunitID": "45012", "reportingunitLevel": 2, "pollClosingTime": "2024-11-06T03:00:00.000000Z", "level": "subunit", "fipsCode": "49023", "electTotal": 6, "lastUpdated": "2024-12-05T19:39:17.391000Z", "precinctsReporting": 31, "eevp": 100.0, "precinctsTotal": 31, "precinctsReportingPct": 100.0, "candidates": [{"candidateID": "8639", "voteCount": 5671, "votePct": 87.01}, {"candidateID": "64984", "voteCount": 734, "votePct": 11.26}, {"candidateID": "167871", "voteCount": 44, "votePct": 0.68}, {"candidateID": "69459", "voteCount": 39, "votePct": 0.6}, {"candidateID": "167488", "voteCount": 10, "votePct": 0.15}, {"candidateID": "895", "voteCount": 10, "votePct": 0.15}, {"candidateID": "73180", "voteCount": 6, "votePct": 0.09}, {"candidateID": "71845", "voteCount": 4, "votePct": 0.06}], "parameters": {"vote": {"expected": {"actual": 6518, "eevpCap": 100.0}, "total": 6518, "registered": 8183}, "precinctsReportingActual": 31, "precinctsReportingProportional": 31}}, "45013": {"statePostal": "UT", "reportingunitName": "Kane", "reportingunitID": "45013", "reportingunitLevel": 2, "pollClosingTime": "2024-11-06T03:00:00.000000Z", "level": "subunit", "fipsCode": "49025", "electTotal": 6, "lastUpdated": "2024-12-05T19:39:17.391000Z", "precinctsReporting": 11, "eevp": 100.0, "precinctsTotal": 11, "precinctsReportingPct": 100.0, "candidates": [{"candidateID": "8639", "voteCount": 3277, "votePct": 73.05}, {"candidateID": "64984", "voteCount": 1137, "votePct": 25.35}, {"candidateID": "69459", "voteCount": 32, "votePct": 0.71}, {"candidateID": "167871", "voteCount": 16, "votePct": 0.36}, {"candidateID": "895", "voteCount": 11, "votePct": 0.25}, {"candidateID": "71845", "voteCount": 6, "votePct": 0.13}, {"candidateID": "73180", "voteCount": 4, "votePct": 0.09}, {"candidateID": "167488", "voteCount": 3, "votePct": 0.07}], "parameters": {"vote": {"expected": {"actual": 4486, "eevpCap": 100.0}, "total": 4486, "registered": 5872}, "precinctsReportingActual": 11, "precinctsReportingProportional": 11}}, "45014": {"statePostal": "UT", "reportingunitName": "Millard", "reportingunitID": "45014", "reportingunitLevel": 2, "pollClosingTime": "2024-11-06T03:00:00.000000Z", "level": "subunit", "fipsCode": "49027", "electTotal": 6, "lastUpdated": "2024-12-05T19:39:17.391000Z", "precinctsReporting": 18, "eevp": 100.0, "precinctsTotal": 18, "precinctsReportingPct": 100.0, "candidates": [{"candidateID": "8639", "voteCount": 5558, "votePct": 87.05}, {"candidateID": "64984", "voteCount": 713, "votePct": 11.17}, {"candidateID": "69459", "voteCount": 45, "votePct": 0.7}, {"candidateID": "167871", "voteCount": 42, "votePct": 0.66}, {"candidateID": "167488", "voteCount": 9, "votePct": 0.14}, {"candidateID": "73180", "voteCount": 8, "votePct": 0.13}, {"candidateID": "895", "voteCount": 8, "votePct": 0.13}, {"candidateID": "71845", "voteCount": 2, "votePct": 0.03}], "parameters": {"vote": {"expected": {"actual": 6385, "eevpCap": 100.0}, "total": 6385, "registered": 8016}, "precinctsReportingActual": 18, "precinctsReportingProportional": 18}}, "45015": {"statePostal": "UT", "reportingunitName": "Morgan", "reportingunitID": "45015", "reportingunitLevel": 2, "pollClosingTime": "2024-11-06T03:00:00.000000Z", "level": "subunit", "fipsCode": "49029", "electTotal": 6, "lastUpdated": "2024-12-05T19:39:17.391000Z", "precinctsReporting": 25, "eevp": 100.0, "precinctsTotal": 25, "precinctsReportingPct": 100.0, "candidates": [{"candidateID": "8639", "voteCount": 5300, "votePct": 78.44}, {"candidateID": "64984", "voteCount": 1256, "votePct": 18.59}, {"candidateID": "69459", "voteCount": 104, "votePct": 1.54}, {"candidateID": "167871", "voteCount": 60, "votePct": 0.89}, {"candidateID": "895", "voteCount": 22, "votePct": 0.33}, {"candidateID": "167488", "voteCount": 10, "votePct": 0.15}, {"candidateID": "73180", "voteCount": 3, "votePct": 0.04}, {"candidateID": "71845", "voteCount": 2, "votePct": 0.03}], "parameters": {"vote": {"expected": {"actual": 6757, "eevpCap": 100.0}, "total": 6757, "registered": 8573}, "precinctsReportingActual": 25, "precinctsReportingProportional": 25}}, "45016": {"statePostal": "UT", "reportingunitName": "Piute", "reportingunitID": "45016", "reportingunitLevel": 2, "pollClosingTime": "2024-11-06T03:00:00.000000Z", "level": "subunit", "fipsCode": "49031", "electTotal": 6, "lastUpdated": "2024-12-05T19:39:17.391000Z", "precinctsReporting": 6, "eevp": 100.0, "precinctsTotal": 6, "precinctsReportingPct": 100.0, "candidates": [{"candidateID": "8639", "voteCount": 854, "votePct": 88.68}, {"candidateID": "64984", "voteCount": 94, "votePct": 9.76}, {"candidateID": "167871", "voteCount": 6, "votePct": 0.62}, {"candidateID": "895", "voteCount": 4, "votePct": 0.42}, {"candidateID": "69459", "voteCount": 3, "votePct": 0.31}, {"candidateID": "167488", "voteCount": 2, "votePct": 0.21}, {"candidateID": "71845", "voteCount": 0, "votePct": 0.0}, {"candidateID": "73180", "voteCount": 0, "votePct": 0.0}], "parameters": {"vote": {"expected": {"actual": 963, "eevpCap": 100.0}, "total": 963, "registered": 1115}, "precinctsReportingActual": 6, "precinctsReportingProportional": 6}}, "45017": {"statePostal": "UT", "reportingunitName": "Rich", "reportingunitID": "45017", "reportingunitLevel": 2, "pollClosingTime": "2024-11-06T03:00:00.000000Z", "level": "subunit", "fipsCode": "49033", "electTotal": 6, "lastUpdated": "2024-12-05T19:39:17.391000Z", "precinctsReporting": 12, "eevp": 100.0, "precinctsTotal": 12, "precinctsReportingPct": 100.0, "candidates": [{"candidateID": "8639", "voteCount": 1211, "votePct": 83.69}, {"candidateID": "64984", "voteCount": 214, "votePct": 14.79}, {"candidateID": "69459", "voteCount": 13, "votePct": 0.9}, {"candidateID": "167488", "voteCount": 4, "votePct": 0.28}, {"candidateID": "895", "voteCount": 3, "votePct": 0.21}, {"candidateID": "167871", "voteCount": 2, "votePct": 0.14}, {"candidateID": "71845", "voteCount": 0, "votePct": 0.0}, {"candidateID": "73180", "voteCount": 0, "votePct": 0.0}], "parameters": {"vote": {"expected": {"actual": 1447, "eevpCap": 100.0}, "total": 1447, "registered": 1670}, "precinctsReportingActual": 12, "precinctsReportingProportional": 12}}, "45018": {"statePostal": "UT", "reportingunitName": "Salt Lake", "reportingunitID": "45018", "reportingunitLevel": 2, "pollClosingTime": "2024-11-06T03:00:00.000000Z", "level": "subunit", "fipsCode": "49035", "electTotal": 6, "lastUpdated": "2024-12-05T19:39:17.391000Z", "precinctsReporting": 983, "eevp": 100.0, "precinctsTotal": 983, "precinctsReportingPct": 100.0, "candidates": [{"candidateID": "64984", "voteCount": 273658, "votePct": 53.71}, {"candidateID": "8639", "voteCount": 221555, "votePct": 43.49}, {"candidateID": "69459", "voteCount": 5260, "votePct": 1.03}, {"candidateID": "895", "voteCount": 3581, "votePct": 0.7}, {"candidateID": "167871", "voteCount": 2090, "votePct": 0.41}, {"candidateID": "73180", "voteCount": 1437, "votePct": 0.28}, {"candidateID": "167488", "voteCount": 990, "votePct": 0.19}, {"candidateID": "71845", "voteCount": 921, "votePct": 0.18}], "parameters": {"vote": {"expected": {"actual": 509492, "eevpCap": 100.0}, "total": 509492, "registered": 698892}, "precinctsReportingActual": 983, "precinctsReportingProportional": 983}}, "45019": {"statePostal": "UT", "reportingunitName": "San Juan", "reportingunitID": "45019", "reportingunitLevel": 2, "pollClosingTime": "2024-11-06T03:00:00.000000Z", "level": "subunit", "fipsCode": "49037", "electTotal": 6, "lastUpdated": "2024-12-05T19:39:17.391000Z", "precinctsReporting": 25, "eevp": 100.0, "precinctsTotal": 25, "precinctsReportingPct": 100.0, "candidates": [{"candidateID": "8639", "voteCount": 3613, "votePct": 57.1}, {"candidateID": "64984", "voteCount": 2581, "votePct": 40.79}, {"candidateID": "69459", "voteCount": 39, "votePct": 0.62}, {"candidateID": "167871", "voteCount": 32, "votePct": 0.51}, {"candidateID": "73180", "voteCount": 23, "votePct": 0.36}, {"candidateID": "71845", "voteCount": 16, "votePct": 0.25}, {"candidateID": "895", "voteCount": 14, "votePct": 0.22}, {"candidateID": "167488", "voteCount": 10, "votePct": 0.16}], "parameters": {"vote": {"expected": {"actual": 6328, "eevpCap": 100.0}, "total": 6328, "registered": 8938}, "precinctsReportingActual": 25, "precinctsReportingProportional": 25}}, "45020": {"statePostal": "UT", "reportingunitName": "Sanpete", "reportingunitID": "45020", "reportingunitLevel": 2, "pollClosingTime": "2024-11-06T03:00:00.000000Z", "level": "subunit", "fipsCode": "49039", "electTotal": 6, "lastUpdated": "2024-12-05T19:39:17.391000Z", "precinctsReporting": 29, "eevp": 100.0, "precinctsTotal": 29, "precinctsReportingPct": 100.0, "candidates": [{"candidateID": "8639", "voteCount": 10653, "votePct": 82.31}, {"candidateID": "64984", "voteCount": 1906, "votePct": 14.73}, {"candidateID": "167871", "voteCount": 197, "votePct": 1.52}, {"candidateID": "69459", "voteCount": 101, "votePct": 0.78}, {"candidateID": "895", "voteCount": 35, "votePct": 0.27}, {"candidateID": "73180", "voteCount": 19, "votePct": 0.15}, {"candidateID": "71845", "voteCount": 17, "votePct": 0.13}, {"candidateID": "167488", "voteCount": 15, "votePct": 0.12}], "parameters": {"vote": {"expected": {"actual": 12943, "eevpCap": 100.0}, "total": 12943, "registered": 16898}, "precinctsReportingActual": 29, "precinctsReportingProportional": 29}}, "45021": {"statePostal": "UT", "reportingunitName": "Sevier", "reportingunitID": "45021", "reportingunitLevel": 2, "pollClosingTime": "2024-11-06T03:00:00.000000Z", "level": "subunit", "fipsCode": "49041", "electTotal": 6, "lastUpdated": "2024-12-05T19:39:17.391000Z", "precinctsReporting": 24, "eevp": 100.0, "precinctsTotal": 24, "precinctsReportingPct": 100.0, "candidates": [{"candidateID": "8639", "voteCount": 9526, "votePct": 87.19}, {"candidateID": "64984", "voteCount": 1236, "votePct": 11.31}, {"candidateID": "69459", "voteCount": 64, "votePct": 0.59}, {"candidateID": "167871", "voteCount": 47, "votePct": 0.43}, {"candidateID": "895", "voteCount": 27, "votePct": 0.25}, {"candidateID": "167488", "voteCount": 11, "votePct": 0.1}, {"candidateID": "73180", "voteCount": 11, "votePct": 0.1}, {"candidateID": "71845", "voteCount": 4, "votePct": 0.04}], "parameters": {"vote": {"expected": {"actual": 10926, "eevpCap": 100.0}, "total": 10926, "registered": 13870}, "precinctsReportingActual": 24, "precinctsReportingProportional": 24}}, "45022": {"statePostal": "UT", "reportingunitName": "Summit", "reportingunitID": "45022", "reportingunitLevel": 2, "pollClosingTime": "2024-11-06T03:00:00.000000Z", "level": "subunit", "fipsCode": "49043", "electTotal": 6, "lastUpdated": "2024-12-05T19:39:17.391000Z", "precinctsReporting": 79, "eevp": 100.0, "precinctsTotal": 79, "precinctsReportingPct": 100.0, "candidates": [{"candidateID": "64984", "voteCount": 14612, "votePct": 56.47}, {"candidateID": "8639", "voteCount": 10783, "votePct": 41.67}, {"candidateID": "69459", "voteCount": 236, "votePct": 0.91}, {"candidateID": "895", "voteCount": 121, "votePct": 0.47}, {"candidateID": "167871", "voteCount": 46, "votePct": 0.18}, {"candidateID": "167488", "voteCount": 36, "votePct": 0.14}, {"candidateID": "71845", "voteCount": 23, "votePct": 0.09}, {"candidateID": "73180", "voteCount": 19, "votePct": 0.07}], "parameters": {"vote": {"expected": {"actual": 25876, "eevpCap": 100.0}, "total": 25876, "registered": 33838}, "precinctsReportingActual": 79, "precinctsReportingProportional": 79}}, "45023": {"statePostal": "UT", "reportingunitName": "Tooele", "reportingunitID": "45023", "reportingunitLevel": 2, "pollClosingTime": "2024-11-06T03:00:00.000000Z", "level": "subunit", "fipsCode": "49045", "electTotal": 6, "lastUpdated": "2024-12-05T19:39:17.391000Z", "precinctsReporting": 84, "eevp": 100.0, "precinctsTotal": 84, "precinctsReportingPct": 100.0, "candidates": [{"candidateID": "8639", "voteCount": 23484, "votePct": 69.09}, {"candidateID": "64984", "voteCount": 9560, "votePct": 28.13}, {"candidateID": "69459", "voteCount": 358, "votePct": 1.05}, {"candidateID": "167871", "voteCount": 237, "votePct": 0.7}, {"candidateID": "895", "voteCount": 168, "votePct": 0.49}, {"candidateID": "167488", "voteCount": 79, "votePct": 0.23}, {"candidateID": "73180", "voteCount": 66, "votePct": 0.19}, {"candidateID": "71845", "voteCount": 36, "votePct": 0.11}], "parameters": {"vote": {"expected": {"actual": 33988, "eevpCap": 100.0}, "total": 33988, "registered": 46856}, "precinctsReportingActual": 84, "precinctsReportingProportional": 84}}, "45024": {"statePostal": "UT", "reportingunitName": "Uintah", "reportingunitID": "45024", "reportingunitLevel": 2, "pollClosingTime": "2024-11-06T03:00:00.000000Z", "level": "subunit", "fipsCode": "49047", "electTotal": 6, "lastUpdated": "2024-12-05T19:39:17.391000Z", "precinctsReporting": 30, "eevp": 100.0, "precinctsTotal": 30, "precinctsReportingPct": 100.0, "candidates": [{"candidateID": "8639", "voteCount": 13599, "votePct": 85.9}, {"candidateID": "64984", "voteCount": 1952, "votePct": 12.33}, {"candidateID": "69459", "voteCount": 113, "votePct": 0.71}, {"candidateID": "167871", "voteCount": 84, "votePct": 0.53}, {"candidateID": "895", "voteCount": 33, "votePct": 0.21}, {"candidateID": "167488", "voteCount": 24, "votePct": 0.15}, {"candidateID": "73180", "voteCount": 15, "votePct": 0.09}, {"candidateID": "71845", "voteCount": 11, "votePct": 0.07}], "parameters": {"vote": {"expected": {"actual": 15831, "eevpCap": 100.0}, "total": 15831, "registered": 21386}, "precinctsReportingActual": 30, "precinctsReportingProportional": 30}}, "45025": {"statePostal": "UT", "reportingunitName": "Utah", "reportingunitID": "45025", "reportingunitLevel": 2, "pollClosingTime": "2024-11-06T03:00:00.000000Z", "level": "subunit", "fipsCode": "49049", "electTotal": 6, "lastUpdated": "2024-12-05T19:39:17.391000Z", "precinctsReporting": 498, "eevp": 100.0, "precinctsTotal": 498, "precinctsReportingPct": 100.0, "candidates": [{"candidateID": "8639", "voteCount": 203476, "votePct": 68.29}, {"candidateID": "64984", "voteCount": 84937, "votePct": 28.51}, {"candidateID": "69459", "voteCount": 4397, "votePct": 1.48}, {"candidateID": "167871", "voteCount": 2164, "votePct": 0.73}, {"candidateID": "895", "voteCount": 1582, "votePct": 0.53}, {"candidateID": "73180", "voteCount": 536, "votePct": 0.18}, {"candidateID": "167488", "voteCount": 470, "votePct": 0.16}, {"candidateID": "71845", "voteCount": 382, "votePct": 0.13}], "parameters": {"vote": {"expected": {"actual": 297944, "eevpCap": 100.0}, "total": 297944, "registered": 406805}, "precinctsReportingActual": 498, "precinctsReportingProportional": 498}}, "45026": {"statePostal": "UT", "reportingunitName": "Wasatch", "reportingunitID": "45026", "reportingunitLevel": 2, "pollClosingTime": "2024-11-06T03:00:00.000000Z", "level": "subunit", "fipsCode": "49051", "electTotal": 6, "lastUpdated": "2024-12-05T19:39:17.391000Z", "precinctsReporting": 54, "eevp": 100.0, "precinctsTotal": 54, "precinctsReportingPct": 100.0, "candidates": [{"candidateID": "8639", "voteCount": 11495, "votePct": 62.63}, {"candidateID": "64984", "voteCount": 6459, "votePct": 35.19}, {"candidateID": "69459", "voteCount": 188, "votePct": 1.02}, {"candidateID": "895", "voteCount": 83, "votePct": 0.45}, {"candidateID": "167871", "voteCount": 79, "votePct": 0.43}, {"candidateID": "167488", "voteCount": 23, "votePct": 0.13}, {"candidateID": "71845", "voteCount": 15, "votePct": 0.08}, {"candidateID": "73180", "voteCount": 12, "votePct": 0.07}], "parameters": {"vote": {"expected": {"actual": 18354, "eevpCap": 100.0}, "total": 18354, "registered": 23835}, "precinctsReportingActual": 54, "precinctsReportingProportional": 54}}, "45027": {"statePostal": "UT", "reportingunitName": "Washington", "reportingunitID": "45027", "reportingunitLevel": 2, "pollClosingTime": "2024-11-06T03:00:00.000000Z", "level": "subunit", "fipsCode": "49053", "electTotal": 6, "lastUpdated": "2024-12-05T19:39:17.391000Z", "precinctsReporting": 136, "eevp": 100.0, "precinctsTotal": 136, "precinctsReportingPct": 100.0, "candidates": [{"candidateID": "8639", "voteCount": 73165, "votePct": 75.24}, {"candidateID": "64984", "voteCount": 22327, "votePct": 22.96}, {"candidateID": "69459", "voteCount": 719, "votePct": 0.74}, {"candidateID": "167871", "voteCount": 447, "votePct": 0.46}, {"candidateID": "895", "voteCount": 294, "votePct": 0.3}, {"candidateID": "167488", "voteCount": 105, "votePct": 0.11}, {"candidateID": "73180", "voteCount": 105, "votePct": 0.11}, {"candidateID": "71845", "voteCount": 81, "votePct": 0.08}], "parameters": {"vote": {"expected": {"actual": 97243, "eevpCap": 100.0}, "total": 97243, "registered": 127591}, "precinctsReportingActual": 136, "precinctsReportingProportional": 136}}, "45028": {"statePostal": "UT", "reportingunitName": "Wayne", "reportingunitID": "45028", "reportingunitLevel": 2, "pollClosingTime": "2024-11-06T03:00:00.000000Z", "level": "subunit", "fipsCode": "49055", "electTotal": 6, "lastUpdated": "2024-12-05T19:39:17.391000Z", "precinctsReporting": 8, "eevp": 100.0, "precinctsTotal": 8, "precinctsReportingPct": 100.0, "candidates": [{"candidateID": "8639", "voteCount": 1238, "votePct": 74.98}, {"candidateID": "64984", "voteCount": 381, "votePct": 23.08}, {"candidateID": "167871", "voteCount": 10, "votePct": 0.61}, {"candidateID": "69459", "voteCount": 8, "votePct": 0.48}, {"candidateID": "71845", "voteCount": 6, "votePct": 0.36}, {"candidateID": "895", "voteCount": 5, "votePct": 0.3}, {"candidateID": "73180", "voteCount": 2, "votePct": 0.12}, {"candidateID": "167488", "voteCount": 1, "votePct": 0.06}], "parameters": {"vote": {"expected": {"actual": 1651, "eevpCap": 100.0}, "total": 1651, "registered": 1947}, "precinctsReportingActual": 8, "precinctsReportingProportional": 8}}, "45029": {"statePostal": "UT", "reportingunitName": "Weber", "reportingunitID": "45029", "reportingunitLevel": 2, "pollClosingTime": "2024-11-06T03:00:00.000000Z", "level": "subunit", "fipsCode": "49057", "electTotal": 6, "lastUpdated": "2024-12-05T19:39:17.391000Z", "precinctsReporting": 180, "eevp": 100.0, "precinctsTotal": 180, "precinctsReportingPct": 100.0, "candidates": [{"candidateID": "8639", "voteCount": 67549, "votePct": 60.3}, {"candidateID": "64984", "voteCount": 41238, "votePct": 36.81}, {"candidateID": "69459", "voteCount": 1325, "votePct": 1.18}, {"candidateID": "895", "voteCount": 644, "votePct": 0.57}, {"candidateID": "167871", "voteCount": 580, "votePct": 0.52}, {"candidateID": "73180", "voteCount": 258, "votePct": 0.23}, {"candidateID": "167488", "voteCount": 234, "votePct": 0.21}, {"candidateID": "71845", "voteCount": 189, "votePct": 0.17}], "parameters": {"vote": {"expected": {"actual": 112017, "eevpCap": 100.0}, "total": 112017, "registered": 153284}, "precinctsReportingActual": 180, "precinctsReportingProportional": 180}}, "summary": {"statePostal": "UT", "stateName": "Utah", "reportingunitID": "45", "reportingunitLevel": 1, "pollClosingTime": "2024-11-06T03:00:00.000000Z", "level": "state", "electTotal": 6, "lastUpdated": "2024-12-05T19:39:17.391000Z", "precinctsReporting": 3105, "eevp": 100.0, "precinctsTotal": 3105, "precinctsReportingPct": 100.0, "candidates": [{"candidateID": "8639", "voteCount": 883818, "winner": "X", "electWon": 6, "votePct": 59.4, "calledAt": "2024-11-06T03:00:09.348Z", "colorIndex": 0}, {"candidateID": "64984", "voteCount": 562566, "votePct": 37.81, "colorIndex": 1}, {"candidateID": "69459", "voteCount": 16902, "votePct": 1.14}, {"candidateID": "167871", "voteCount": 8402, "votePct": 0.56}, {"candidateID": "895", "voteCount": 8222, "votePct": 0.55}, {"candidateID": "73180", "voteCount": 3189, "votePct": 0.21}, {"candidateID": "167488", "voteCount": 2653, "votePct": 0.18}, {"candidateID": "71845", "voteCount": 2199, "votePct": 0.15}], "parameters": {"vote": {"expected": {"actual": 1487951, "eevpCap": 100.0}, "total": 1487951, "registered": 2011364}, "precinctsReportingActual": 3105, "precinctsReportingProportional": 3105}, "raceID": "20241105UT0", "test": false, "resultsType": "certified"}}